[
  {
    "01": [
      "学生",
      "HH"
    ],
    "02": [
      "基調",
      "LL"
    ],
    "03": [
      "冷屋",
      "NW"
    ],
    "04": [
      "制限",
      "HL"
    ],
    "05": [
      "外士",
      "NW"
    ],
    "06": [
      "主草",
      "NW"
    ],
    "07": [
      "自重",
      "LL"
    ],
    "08": [
      "生海",
      "NW"
    ],
    "09": [
      "音博",
      "NW"
    ],
    "10": [
      "当時",
      "HL"
    ],
    "11": [
      "想録",
      "NW"
    ],
    "12": [
      "常益",
      "NW"
    ],
    "13": [
      "手術",
      "HH"
    ],
    "14": [
      "逆転",
      "LL"
    ],
    "15": [
      "金属",
      "HH"
    ],
    "16": [
      "巻器",
      "NW"
    ],
    "17": [
      "戦争",
      "HH"
    ],
    "18": [
      "識文",
      "NW"
    ],
    "19": [
      "車園",
      "NW"
    ],
    "20": [
      "田園",
      "LH"
    ],
    "21": [
      "状態",
      "HL"
    ],
    "22": [
      "水泳",
      "LH"
    ],
    "23": [
      "続基",
      "NW"
    ],
    "24": [
      "通学",
      "LH"
    ],
    "25": [
      "福供",
      "NW"
    ],
    "26": [
      "発想",
      "LL"
    ],
    "27": [
      "永調",
      "NW"
    ],
    "28": [
      "夫婦",
      "HH"
    ],
    "29": [
      "結果",
      "HL"
    ],
    "30": [
      "具血",
      "NW"
    ],
    "31": [
      "自安",
      "NW"
    ],
    "32": [
      "思想",
      "HL"
    ],
    "33": [
      "選定",
      "LL"
    ],
    "34": [
      "果樹",
      "LH"
    ],
    "35": [
      "職価",
      "NW"
    ],
    "36": [
      "関係",
      "HL"
    ],
    "37": [
      "信用",
      "HL"
    ],
    "38": [
      "済囲",
      "NW"
    ],
    "39": [
      "講製",
      "NW"
    ],
    "40": [
      "当態",
      "NW"
    ],
    "41": [
      "放送",
      "HH"
    ],
    "42": [
      "海外",
      "HH"
    ],
    "43": [
      "発収",
      "NW"
    ],
    "44": [
      "種類",
      "HL"
    ],
    "45": [
      "温泉",
      "HH"
    ],
    "46": [
      "所学",
      "NW"
    ],
    "47": [
      "車楽",
      "NW"
    ],
    "48": [
      "制化",
      "NW"
    ],
    "49": [
      "控室",
      "LH"
    ],
    "50": [
      "場花",
      "NW"
    ],
    "51": [
      "役火",
      "NW"
    ],
    "52": [
      "収益",
      "HL"
    ],
    "53": [
      "泳田",
      "NW"
    ],
    "54": [
      "定外",
      "NW"
    ],
    "55": [
      "船長",
      "LH"
    ],
    "56": [
      "演幸",
      "NW"
    ],
    "57": [
      "親戚",
      "LH"
    ],
    "58": [
      "精製",
      "LL"
    ],
    "59": [
      "察手",
      "NW"
    ],
    "60": [
      "冷凍",
      "LH"
    ],
    "61": [
      "経済",
      "HL"
    ],
    "62": [
      "水内",
      "NW"
    ],
    "63": [
      "気思",
      "NW"
    ],
    "64": [
      "夫送",
      "NW"
    ],
    "65": [
      "講和",
      "LL"
    ],
    "66": [
      "病温",
      "NW"
    ],
    "67": [
      "幸福",
      "HH"
    ],
    "68": [
      "笑長",
      "NW"
    ],
    "69": [
      "種収",
      "NW"
    ],
    "70": [
      "味想",
      "NW"
    ],
    "71": [
      "収録",
      "LL"
    ],
    "72": [
      "役所",
      "LH"
    ],
    "73": [
      "主元",
      "NW"
    ],
    "74": [
      "保安",
      "LL"
    ],
    "75": [
      "職権",
      "LL"
    ],
    "76": [
      "写真",
      "HH"
    ],
    "77": [
      "前類",
      "NW"
    ],
    "78": [
      "望閉",
      "NW"
    ],
    "79": [
      "場列",
      "NW"
    ],
    "80": [
      "屋上",
      "LH"
    ],
    "81": [
      "必信",
      "NW"
    ],
    "82": [
      "条項",
      "LL"
    ],
    "83": [
      "周囲",
      "HL"
    ],
    "84": [
      "説婦",
      "NW"
    ],
    "85": [
      "意結",
      "NW"
    ],
    "86": [
      "選案",
      "NW"
    ],
    "87": [
      "葉巻",
      "LH"
    ],
    "88": [
      "状個",
      "NW"
    ],
    "89": [
      "協経",
      "NW"
    ],
    "90": [
      "容器",
      "LH"
    ],
    "91": [
      "子供",
      "HH"
    ],
    "92": [
      "学真",
      "NW"
    ],
    "93": [
      "草案",
      "LL"
    ],
    "94": [
      "外観",
      "LLL"
    ],
    "95": [
      "主眼",
      "LL"
    ],
    "96": [
      "属写",
      "NW"
    ],
    "97": [
      "保判",
      "NW"
    ],
    "98": [
      "必要",
      "HL"
    ],
    "99": [
      "音楽",
      "HH"
    ],
    "100": [
      "火花",
      "LH"
    ],
    "101": [
      "限要",
      "NW"
    ],
    "102": [
      "項持",
      "NW"
    ],
    "103": [
      "文化",
      "HL"
    ],
    "104": [
      "演奏",
      "HH"
    ],
    "105": [
      "口逆",
      "NW"
    ],
    "106": [
      "協定",
      "HL"
    ],
    "107": [
      "原眼",
      "NW"
    ],
    "108": [
      "小鳥",
      "LH"
    ],
    "109": [
      "公観",
      "NW"
    ],
    "110": [
      "警察",
      "HH"
    ],
    "111": [
      "売場",
      "LH"
    ],
    "112": [
      "永続",
      "LL"
    ],
    "113": [
      "重和",
      "NW"
    ],
    "114": [
      "時係",
      "NW"
    ],
    "115": [
      "絵凍",
      "NW"
    ],
    "116": [
      "原価",
      "LL"
    ],
    "117": [
      "公平",
      "LL"
    ],
    "118": [
      "劇屋",
      "NW"
    ],
    "119": [
      "戚小",
      "NW"
    ],
    "120": [
      "個人",
      "HL"
    ],
    "121": [
      "鳥舟",
      "NW"
    ],
    "122": [
      "常識",
      "HL"
    ],
    "123": [
      "人関",
      "NW"
    ],
    "124": [
      "判例",
      "LL"
    ],
    "125": [
      "博士",
      "HH"
    ],
    "126": [
      "主義",
      "HL"
    ],
    "127": [
      "精平",
      "NW"
    ],
    "128": [
      "出血",
      "LH"
    ],
    "129": [
      "転条",
      "NW"
    ],
    "130": [
      "小説",
      "HH"
    ],
    "131": [
      "爆笑",
      "LH"
    ],
    "132": [
      "元気",
      "HL"
    ],
    "133": [
      "戦放",
      "NW"
    ],
    "134": [
      "通室",
      "NW"
    ],
    "135": [
      "気子",
      "NW"
    ],
    "136": [
      "意味",
      "HL"
    ],
    "137": [
      "爆控",
      "NW"
    ],
    "138": [
      "病気",
      "HH"
    ],
    "139": [
      "車内",
      "LH"
    ],
    "140": [
      "後定",
      "NW"
    ],
    "141": [
      "奏術",
      "NW"
    ],
    "142": [
      "用果",
      "NW"
    ],
    "143": [
      "絵具",
      "LH"
    ],
    "144": [
      "果出",
      "NW"
    ],
    "145": [
      "閉口",
      "LL"
    ],
    "146": [
      "部屋",
      "HH"
    ],
    "147": [
      "警小",
      "NW"
    ],
    "148": [
      "劇場",
      "HH"
    ],
    "149": [
      "前後",
      "HL"
    ],
    "150": [
      "体葉",
      "NW"
    ],
    "151": [
      "列車",
      "HH"
    ],
    "152": [
      "親売",
      "NW"
    ],
    "153": [
      "周義",
      "NW"
    ],
    "154": [
      "容上",
      "NW"
    ],
    "155": [
      "人体",
      "LH"
    ],
    "156": [
      "金争",
      "NW"
    ],
    "157": [
      "権例",
      "NW"
    ],
    "158": [
      "人樹",
      "NW"
    ],
    "159": [
      "待望",
      "LL"
    ],
    "160": [
      "部泉",
      "NW"
    ]
  },
  {
    "01": [
      "こより",
      ""
    ],
    "02": [
      "よもい",
      "（よろい）"
    ],
    "03": [
      "ゆのみ",
      ""
    ],
    "04": [
      "たきぎ",
      ""
    ],
    "05": [
      "あつび",
      "（あくび）"
    ],
    "06": [
      "けむに",
      " (けむり)"
    ],
    "07": [
      "わらじ",
      ""
    ],
    "08": [
      "いとろ",
      "（いとこ）"
    ],
    "09": [
      "みきん",
      "（みりん）"
    ],
    "10": [
      "なだけ",
      "（なだれ）"
    ],
    "11": [
      "かがみ",
      ""
    ],
    "12": [
      "もさか",
      "（とさか）"
    ],
    "13": [
      "あくび",
      ""
    ],
    "14": [
      "よぶし",
      "（こぶし）"
    ],
    "15": [
      "たがみ",
      "（かがみ）"
    ],
    "16": [
      "あらし",
      ""
    ],
    "17": [
      "みりん",
      ""
    ],
    "18": [
      "とさか",
      ""
    ],
    "19": [
      "わぶと",
      "（かぶと）"
    ],
    "20": [
      "けむり",
      ""
    ],
    "21": [
      "あまし",
      "（あらし）"
    ],
    "22": [
      "うどん",
      ""
    ],
    "23": [
      "こよち",
      "（こより）"
    ],
    "24": [
      "のれん",
      ""
    ],
    "25": [
      "むしろ",
      ""
    ],
    "26": [
      "やぶら",
      "（やぐら）"
    ],
    "27": [
      "なだれ",
      ""
    ],
    "28": [
      "うごん",
      " (うどん)"
    ],
    "29": [
      "たきり",
      " (たきぎ)"
    ],
    "30": [
      "いとこ",
      ""
    ],
    "31": [
      "うちわ",
      ""
    ],
    "32": [
      "たらじ",
      "（わらじ）"
    ],
    "33": [
      "くのみ",
      "（ゆのみ）"
    ],
    "34": [
      "ゆしろ",
      "（むしろ）"
    ],
    "35": [
      "かぶと",
      ""
    ],
    "36": [
      "こぶし",
      ""
    ],
    "37": [
      "よろい",
      ""
    ],
    "38": [
      "うちな",
      "（うちわ）"
    ],
    "39": [
      "やぐら",
      ""
    ],
    "40": [
      "のけん",
      "（のれん）"
    ]
  },
  {
    "01": [
      "きいび",
      "（いびき）"
    ],
    "02": [
      "とびら",
      ""
    ],
    "03": [
      "ろいり",
      "（いろり）"
    ],
    "04": [
      "つまげ",
      "（まつげ）"
    ],
    "05": [
      "あられ",
      ""
    ],
    "06": [
      "かかし",
      ""
    ],
    "07": [
      "えくぼ",
      ""
    ],
    "08": [
      "ういが",
      "（うがい）"
    ],
    "09": [
      "けじめ",
      ""
    ],
    "10": [
      "めがね",
      ""
    ],
    "11": [
      "みれぞ",
      "（みぞれ"
    ],
    "12": [
      "まけお",
      "（おまけ）"
    ],
    "13": [
      "つぽみ",
      ""
    ],
    "14": [
      "みげや",
      "（みやげ）"
    ],
    "15": [
      "ねがめ",
      "（めがね）"
    ],
    "16": [
      "ともた",
      "（たもと）"
    ],
    "17": [
      "うわさ",
      ""
    ],
    "18": [
      "きかね",
      "（かきね）"
    ],
    "19": [
      "つくえ",
      ""
    ],
    "20": [
      "かおり",
      ""
    ],
    "21": [
      "うがい",
      ""
    ],
    "22": [
      "みぞれ",
      ""
    ],
    "23": [
      "りかお",
      "（かおり）"
    ],
    "24": [
      "おまけ",
      ""
    ],
    "25": [
      "かきね",
      ""
    ],
    "26": [
      "いろり",
      ""
    ],
    "27": [
      "びとら",
      "（とびら）"
    ],
    "28": [
      "えつく",
      "（つくえ）"
    ],
    "29": [
      "ぼえく",
      "（えくぼ）"
    ],
    "30": [
      "まつげ",
      ""
    ],
    "31": [
      "わさう",
      "（うわさ）"
    ],
    "32": [
      "ぼみつ",
      "（つぼみ）"
    ],
    "33": [
      "かしか",
      "（かかし"
    ],
    "34": [
      "いびき",
      ""
    ],
    "35": [
      "れらあ",
      "（あられ）"
    ],
    "36": [
      "もなか",
      ""
    ],
    "37": [
      "たもと",
      ""
    ],
    "38": [
      "けめじ",
      "（けじめ"
    ],
    "39": [
      "みやげ",
      ""
    ],
    "40": [
      "かなも",
      "（もなか）"
    ]
  },
  {
    "01": [
      "ぬばた",
      "（おわり）"
    ],
    "02": [
      "かけら",
      ""
    ],
    "03": [
      "たちる",
      "（つまみ）"
    ],
    "04": [
      "どびん",
      ""
    ],
    "05": [
      "ねうろ",
      "（みさき）"
    ],
    "06": [
      "ねらい",
      ""
    ],
    "07": [
      "たすき",
      ""
    ],
    "08": [
      "つまみ",
      ""
    ],
    "09": [
      "くじゆ",
      "（かけら)"
    ],
    "10": [
      "うかき",
      "（たばこ）"
    ],
    "11": [
      "おはぎ",
      ""
    ],
    "12": [
      "おさげ",
      ""
    ],
    "13": [
      "とのぐ",
      "（あせも）"
    ],
    "14": [
      "におい",
      ""
    ],
    "15": [
      "よあな",
      "（におい）"
    ],
    "16": [
      "ちりえ",
      "（えがお)"
    ],
    "17": [
      "もやら",
      "（どびん）"
    ],
    "18": [
      "こずえ",
      ""
    ],
    "19": [
      "おわり",
      ""
    ],
    "20": [
      "とでわ",
      "（おさげ）"
    ],
    "21": [
      "ぼにん",
      "（おどり）"
    ],
    "22": [
      "むかし",
      ""
    ],
    "23": [
      "われみ",
      "（むかし）"
    ],
    "24": [
      "まだら",
      ""
    ],
    "25": [
      "みさき",
      ""
    ],
    "26": [
      "おげる",
      "（ねらい）"
    ],
    "27": [
      "てびお",
      "（まとめ）"
    ],
    "28": [
      "てらご",
      "（くぼみ）"
    ],
    "29": [
      "たばこ",
      ""
    ],
    "30": [
      "まとめ",
      ""
    ],
    "31": [
      "きぬが",
      "（まだら）"
    ],
    "32": [
      "のんき",
      ""
    ],
    "33": [
      "あせも",
      ""
    ],
    "34": [
      "くぼみ",
      ""
    ],
    "35": [
      "いねめ",
      "（こずえ）"
    ],
    "36": [
      "おどり",
      ""
    ],
    "37": [
      "くまな",
      "（おはぎ）"
    ],
    "38": [
      "えがお",
      ""
    ],
    "39": [
      "あけむ",
      "（たすき）"
    ],
    "40": [
      "みこれ",
      "（のんき）"
    ]
  },
  {
    "01": [
      "てれび",
      "1000"
    ],
    "02": [
      "とびら",
      "0100"
    ],
    "03": [
      "ものみ",
      "0001"
    ],
    "04": [
      "こゆび",
      "0100"
    ],
    "05": [
      "しょくじ",
      "1000"
    ],
    "06": [
      "よぼう",
      "0010"
    ],
    "07": [
      "でんわ",
      "1000"
    ],
    "08": [
      "ひはん",
      "0010"
    ],
    "09": [
      "はだか",
      "0100"
    ],
    "10": [
      "たいこ",
      "0001"
    ],
    "11": [
      "つごう",
      "0010"
    ],
    "12": [
      "うでわ",
      "0100"
    ],
    "13": [
      "よてい",
      "0010"
    ],
    "14": [
      "めぼし",
      "0001"
    ],
    "15": [
      "ていど",
      "0010"
    ],
    "16": [
      "くるま",
      "1000"
    ],
    "17": [
      "ききめ",
      "0001"
    ],
    "18": [
      "しゃしん",
      "1000"
    ],
    "19": [
      "あひる",
      "0100"
    ],
    "20": [
      "ぐもん",
      "0001"
    ],
    "21": [
      "ろんり",
      "0010"
    ],
    "22": [
      "わがし",
      "0100"
    ],
    "23": [
      "くすり",
      "1000"
    ],
    "24": [
      "ちゃしつ",
      "0100"
    ],
    "25": [
      "めやす",
      "0001"
    ],
    "26": [
      "からだ",
      "1000"
    ],
    "27": [
      "さかき",
      "0001"
    ],
    "28": [
      "きやく",
      "0010"
    ],
    "29": [
      "ひでん",
      "0001"
    ],
    "30": [
      "りゆう",
      "0010"
    ],
    "31": [
      "ぶらく",
      "0001"
    ],
    "32": [
      "あぶら",
      "1000"
    ],
    "33": [
      "ゆびわ",
      "0100"
    ],
    "34": [
      "てがみ",
      "1000"
    ],
    "35": [
      "とりい",
      "0100"
    ],
    "36": [
      "かしつ",
      "0010"
    ],
    "37": [
      "いちば",
      "1000"
    ],
    "38": [
      "ゆみや",
      "0100"
    ],
    "39": [
      "きみつ",
      "0010"
    ],
    "40": [
      "むめい",
      "0001"
    ],
    "41": [
      "げんか",
      "0010"
    ],
    "42": [
      "こども",
      "1000"
    ],
    "43": [
      "びとく",
      "0001"
    ],
    "44": [
      "こんぶ",
      "0100"
    ],
    "45": [
      "ひょうか",
      "0010"
    ],
    "46": [
      "ひとみ",
      "0100"
    ],
    "47": [
      "ゆいしょ",
      "0001"
    ],
    "48": [
      "かざん",
      "1000"
    ],
    "49": [
      "ひろま",
      "0100"
    ],
    "50": [
      "あんじ",
      "0010"
    ],
    "51": [
      "あとめ",
      "0001"
    ],
    "52": [
      "みどり",
      "1000"
    ]
  },
  {
    "01": [
      "パン",
      "kata",
      "2"
    ],
    "02": [
      "信号",
      "kanj",
      "4"
    ],
    "03": [
      "馬",
      "kanj",
      "2"
    ],
    "04": [
      "紅茶",
      "kanj",
      "3"
    ],
    "05": [
      "えび",
      "hira",
      "2"
    ],
    "06": [
      "ポスト",
      "kata",
      "3"
    ],
    "07": [
      "にわとり",
      "hira",
      "4"
    ],
    "08": [
      "耳",
      "kanj",
      "2"
    ],
    "09": [
      "エプロン",
      "kata",
      "4"
    ],
    "10": [
      "牛乳",
      "kanj",
      "4"
    ],
    "11": [
      "たわし",
      "hira",
      "3"
    ],
    "12": [
      "じゃがいも",
      "hira",
      "4"
    ],
    "13": [
      "切手",
      "kanj",
      "3"
    ],
    "14": [
      "バス",
      "kata",
      "2"
    ],
    "15": [
      "ちりとり",
      "hira",
      "4"
    ],
    "16": [
      "アルバム",
      "kata",
      "4"
    ],
    "17": [
      "あご",
      "hira",
      "2"
    ],
    "18": [
      "マスク",
      "kata",
      "3"
    ],
    "19": [
      "毛虫",
      "kanj",
      "3"
    ],
    "20": [
      "りんご",
      "hira",
      "3"
    ],
    "21": [
      "目薬",
      "kanj",
      "4"
    ],
    "22": [
      "バナナ",
      "kata",
      "3"
    ],
    "23": [
      "トンネル",
      "kata",
      "4"
    ],
    "24": [
      "たこ",
      "hira",
      "2"
    ],
    "25": [
      "太陽",
      "kanj",
      "4"
    ],
    "26": [
      "ピザ",
      "kata",
      "2"
    ],
    "27": [
      "はさみ",
      "hira",
      "3"
    ],
    "28": [
      "テレビ",
      "kata",
      "3"
    ],
    "29": [
      "あじさい",
      "hira",
      "4"
    ],
    "30": [
      "こま",
      "hira",
      "2"
    ],
    "31": [
      "カーテン",
      "kata",
      "4"
    ],
    "32": [
      "ねぎ",
      "hira",
      "2"
    ],
    "33": [
      "学校",
      "kanj",
      "4"
    ],
    "34": [
      "タオル",
      "kata",
      "3"
    ],
    "35": [
      "虹",
      "kanj",
      "2"
    ],
    "36": [
      "バラ",
      "kata",
      "2"
    ],
    "37": [
      "水着",
      "kanj",
      "3"
    ],
    "38": [
      "うさぎ",
      "hira",
      "3"
    ],
    "39": [
      "ダム",
      "kata",
      "2"
    ],
    "40": [
      "空",
      "kanj",
      "2"
    ],
    "41": [
      "電話",
      "kanj",
      "3"
    ],
    "42": [
      "ライオン",
      "kata",
      "4"
    ],
    "43": [
      "やかん",
      "hira",
      "3"
    ],
    "44": [
      "指",
      "kanj",
      "2"
    ],
    "45": [
      "おにぎり",
      "hira",
      "4"
    ],
    "46": [
      "ドーナツ",
      "kata",
      "4"
    ],
    "47": [
      "交番",
      "kanj",
      "4"
    ],
    "48": [
      "いちご",
      "hira",
      "3"
    ],
    "49": [
      "ドア",
      "kata",
      "2"
    ],
    "50": [
      "ろうそく",
      "hira",
      "4"
    ],
    "51": [
      "写真",
      "kanj",
      "3"
    ],
    "52": [
      "アンテナ",
      "kata",
      "4"
    ],
    "53": [
      "へそ",
      "hira",
      "2"
    ],
    "54": [
      "のこぎり",
      "hira",
      "4"
    ],
    "55": [
      "コップ",
      "kata",
      "3"
    ],
    "56": [
      "滝",
      "kanj",
      "2"
    ],
    "57": [
      "手紙",
      "kanj",
      "3"
    ],
    "58": [
      "こたつ",
      "hira",
      "3"
    ],
    "59": [
      "牛",
      "kanj",
      "2"
    ],
    "60": [
      "ピアノ",
      "kata",
      "3"
    ],
    "61": [
      "デモ",
      "kata",
      "2"
    ],
    "62": [
      "金魚",
      "kanj",
      "3"
    ],
    "63": [
      "ペン",
      "kata",
      "2"
    ],
    "64": [
      "弁当",
      "kanj",
      "4"
    ],
    "65": [
      "こけし",
      "hira",
      "3"
    ],
    "66": [
      "骨",
      "kanj",
      "2"
    ],
    "67": [
      "朝顔",
      "kanj",
      "4"
    ],
    "68": [
      "ミシン",
      "kata",
      "3"
    ],
    "69": [
      "いか",
      "hira",
      "2"
    ],
    "70": [
      "アイロン",
      "kata",
      "4"
    ],
    "71": [
      "かまぼこ",
      "hira",
      "4"
    ],
    "72": [
      "バット",
      "kata",
      "3"
    ],
    "73": [
      "やぎ",
      "hira",
      "2"
    ],
    "74": [
      "火山",
      "kanj",
      "3"
    ],
    "75": [
      "ネクタイ",
      "kata",
      "4"
    ],
    "76": [
      "窓",
      "kanj",
      "2"
    ],
    "77": [
      "ペンギン",
      "kata",
      "4"
    ],
    "78": [
      "うちわ",
      "hira",
      "3"
    ],
    "79": [
      "灰皿",
      "kanj",
      "4"
    ],
    "80": [
      "ガム",
      "kata",
      "2"
    ],
    "81": [
      "ひまわり",
      "hira",
      "4"
    ],
    "82": [
      "キャベツ",
      "kata",
      "3"
    ],
    "83": [
      "口",
      "kanj",
      "2"
    ],
    "84": [
      "しゃもじ",
      "hira",
      "3"
    ],
    "85": [
      "ふぐ",
      "hira",
      "2"
    ],
    "86": [
      "背中",
      "kanj",
      "3"
    ],
    "87": [
      "なす",
      "hira",
      "2"
    ],
    "88": [
      "そろばん",
      "hira",
      "4"
    ],
    "89": [
      "ハム",
      "kata",
      "2"
    ],
    "90": [
      "病院",
      "kanj",
      "4"
    ]
  },
  {
    "01": [
      "のい",
      "2"
    ],
    "02": [
      "びげ",
      "2"
    ],
    "03": [
      "ずきょ",
      "2"
    ],
    "04": [
      "じず",
      "2"
    ],
    "05": [
      "えも",
      "2"
    ],
    "06": [
      "すお",
      "2"
    ],
    "07": [
      "きゃし",
      "2"
    ],
    "08": [
      "のゆ",
      "2"
    ],
    "09": [
      "けぼ",
      "2"
    ],
    "10": [
      "やび",
      "2"
    ],
    "11": [
      "けぐ",
      "2"
    ],
    "12": [
      "ばべ",
      "2"
    ],
    "13": [
      "けひ",
      "2"
    ],
    "14": [
      "ゆち",
      "2"
    ],
    "15": [
      "とぷか",
      "3"
    ],
    "16": [
      "にょせき",
      "3"
    ],
    "17": [
      "えなぶ",
      "3"
    ],
    "18": [
      "かきふ",
      "3"
    ],
    "19": [
      "こうな",
      "3"
    ],
    "20": [
      "ねっけ",
      "3"
    ],
    "21": [
      "くらが",
      "3"
    ],
    "22": [
      "ふけの",
      "3"
    ],
    "23": [
      "めひゃく",
      "3"
    ],
    "24": [
      "いいと",
      "3"
    ],
    "25": [
      "くれみゅ",
      "3"
    ],
    "26": [
      "みった",
      "3"
    ],
    "27": [
      "すんき",
      "3"
    ],
    "28": [
      "らげん",
      "3"
    ],
    "29": [
      "いまそし",
      "4"
    ],
    "30": [
      "りゃくしけ",
      "4"
    ],
    "31": [
      "にっさき",
      "4"
    ],
    "32": [
      "ざっこり",
      "4"
    ],
    "33": [
      "びかゆう",
      "4"
    ],
    "34": [
      "さねきり",
      "4"
    ],
    "35": [
      "けだずり",
      "4"
    ],
    "36": [
      "きっこく",
      "4"
    ],
    "37": [
      "ぱころね",
      "4"
    ],
    "38": [
      "いかたん",
      "4"
    ],
    "39": [
      "ねいたく",
      "4"
    ],
    "40": [
      "てずしな",
      "4"
    ],
    "41": [
      "ひごちゃに",
      "4"
    ],
    "42": [
      "ふばんず",
      "4"
    ],
    "43": [
      "さかじょがた",
      "5"
    ],
    "44": [
      "まとびこう",
      "5"
    ],
    "45": [
      "しごふうか",
      "5"
    ],
    "46": [
      "かすじごと",
      "5"
    ],
    "47": [
      "ごふれがん",
      "5"
    ],
    "48": [
      "なかしりん",
      "5"
    ],
    "49": [
      "おんさつか",
      "5"
    ],
    "50": [
      "きゅらぶっし",
      "5"
    ],
    "51": [
      "しっつくみ",
      "5"
    ],
    "52": [
      "ふせざわり",
      "5"
    ],
    "53": [
      "きなくさら",
      "5"
    ],
    "54": [
      "つきのとめ",
      "5"
    ],
    "55": [
      "えなふりぎょ",
      "5"
    ],
    "56": [
      "しきっぱく",
      "5"
    ]
  }
]